rexmind/__init__.py
rexmind/rexmind.py
rexmind-0.0.3.dist-info/LICENSE
rexmind-0.0.3.dist-info/METADATA
rexmind-0.0.3.dist-info/WHEEL
rexmind-0.0.3.dist-info/top_level.txt
rexmind-0.0.3.dist-info/RECORD
